{
  "identifiers": {
    "internal_id": "137",
    "note": "internal_id is the bdlaws database identifier, not the legal citation number"
  },
  "title_raw": "The Carriage of Goods by Sea Act, 1925",
  "title_normalized": "The Carriage of Goods by Sea Act, 1925",
  "content_raw": "The Carriage of Goods by Sea Act, 1925 \n\n                        \n                        \n                    \n                    \n                        \n                        \n                        \n                        \n                        \n                        \n                        \n                        \n                        \n                        \n                        \n                        \n                        \n                             (\n                                \n                                    \n                                    \n                                        \n                                            \n                                            ACT\n                                        \n                                        NO. XXVI OF 1925\n                                    \n                                \n\n                                )\n\n1♣An Act to amend the law with respect to the carriage of goods by sea.\n\n                                    \n                                    \n                                \n                            \n                        \n                        \n                            \n                            \n                                 \tWHEREAS at the International Conference on Maritime Law held at Brussels in October, 1922, the delegates at the Conference, including the delegates representing His majesty, agree unanimously to recommend their respective Governments to adopt as the basis of a convention a draft convention for the unification of certain rules relating to bills of lading;   \tAND WHEREAS at a meeting held at Brussels in October, 1923, the rules contained in the said draft convention were amended by the Committee appointed by said Conference;   \tAND WHEREAS provision has been made by the Carriage of Goods by Sea Act, 1924, that the said rules as so amended and as set out with modifications in the Schedule shall, subject to the provisions of that Act, have the force of law with a view to establishing the responsibilities, liabilities, rights and immunities attaching to carriers under bills of lading;   \tAND WHEREAS it is expedient that like provision should be made in Bangladesh; It is hereby enacted as follows:-\n\n1♣An Act to amend the law with respect to the carriage of goods by sea.\n\nShort title and extent\n1.(1) This Act may be called the Carriage of Goods by Sea Act, 1925.  \t(2) \tIt extends to the whole of Bangladesh.\n\nApplication of Rules\n2. \tSubject to the provisions of this Act, the rules set out in the Schedule (hereinafter referred to as \" the Rules\") shall have effect in relation to and in connection with the carriage of goods by sea in ships carrying goods from any port in Bangladesh to any other port whether in or outside Bangladesh.\n\nAbsolute warranty of seaworthiness not to be implied in contracts to which Rules apply\n3. There shall not be implied in any contract for the carriage of goods by sea to which the Rules apply any absolute undertaking by the carrier of the goods to provide a seaworthy ship.\n\nStatement as to application of Rules to be included in bills of lading\n4. \tEvery bill of lading, or similar document of title, issued in Bangladesh which contains or is evidence of any contract to which the Rules apply, shall contain an express statement that it is to have effect subject to the provisions of the said Rules as applied by this Act.\n\nModification of Article VI of Rules in relation to goods carried in sailing ships and by prescribed routes\n5. \tArticle VI of the Rules shall, in relation to-  (a) \tthe carriage of goods by sea in sailing ships carrying goods from any port in Bangladesh to any other port whether in or outside Bangladesh, and   (b) \tthe carriage of goods by sea in ships carrying goods from a port in Bangladesh notified in this behalf in the official Gazette by the Government to a port  2[in India, Ceylon or Pakistan] specified in the said notification,  have effect as though the said Article referred to goods any class instead of to particular goods and as though the proviso to the second paragraph of the said Article were omitted.\n\nModification of Rules 4 and 5 of Article III in relation to bulk cargoes\n6. Where under the custom of any trade the weight of any bulk cargo inserted in the bill of lading is a weight ascertained or accepted by a third party other than the carrier or the shipper and the fact that the weight is so ascertained or accepted is stated in the bill of lading, then, notwithstanding anything in the Rules, the bill of lading shall not be deemed to be prima facie evidence against the carrier of the receipt of goods of the weight so inserted in the bill of lading, and the accuracy thereof at the time of shipment shall not be deemed to have been guaranteed by the shipper.\n\nSaving and operation\n7.(1) Nothing in this Act shall affect the operation of sections four hundred and forty six to four hundred and fifty, both inclusive, five hundred and two, and five hundred and three of the Merchant Shipping Act, 1894, as amended by any subsequent enactment, or the operation of any other enactment for the time being in force limiting the liability of the owners of sea-going vessels.   \t(2) \tThe Rules shall not be virtue of this Act apply to any contract for the carriage of goods by sea before such day, not being earlier than the first day of January, 1926, as the Government may, by notification in the official Gazette, appoint, nor to any bill of lading or similar document of title issued, whether before or after such day as aforesaid, in pursuance of any such contract as aforesaid.",
  "content_normalized": "The Carriage of Goods by Sea Act, 1925 \n\n                        \n                        \n                    \n                    \n                        \n                        \n                        \n                        \n                        \n                        \n                        \n                        \n                        \n                        \n                        \n                        \n                        \n                             (\n                                \n                                    \n                                    \n                                        \n                                            \n                                            ACT\n                                        \n                                        NO. XXVI OF 1925\n                                    \n                                \n\n                                )\n\n1♣An Act to amend the law with respect to the carriage of goods by sea.\n\n                                    \n                                    \n                                \n                            \n                        \n                        \n                            \n                            \n                                 \tWHEREAS at the International Conference on Maritime Law held at Brussels in October, 1922, the delegates at the Conference, including the delegates representing His majesty, agree unanimously to recommend their respective Governments to adopt as the basis of a convention a draft convention for the unification of certain rules relating to bills of lading;   \tAND WHEREAS at a meeting held at Brussels in October, 1923, the rules contained in the said draft convention were amended by the Committee appointed by said Conference;   \tAND WHEREAS provision has been made by the Carriage of Goods by Sea Act, 1924, that the said rules as so amended and as set out with modifications in the Schedule shall, subject to the provisions of that Act, have the force of law with a view to establishing the responsibilities, liabilities, rights and immunities attaching to carriers under bills of lading;   \tAND WHEREAS it is expedient that like provision should be made in Bangladesh; It is hereby enacted as follows:-\n\n1♣An Act to amend the law with respect to the carriage of goods by sea.\n\nShort title and extent\n1.(1) This Act may be called the Carriage of Goods by Sea Act, 1925.  \t(2) \tIt extends to the whole of Bangladesh.\n\nApplication of Rules\n2. \tSubject to the provisions of this Act, the rules set out in the Schedule (hereinafter referred to as \" the Rules\") shall have effect in relation to and in connection with the carriage of goods by sea in ships carrying goods from any port in Bangladesh to any other port whether in or outside Bangladesh.\n\nAbsolute warranty of seaworthiness not to be implied in contracts to which Rules apply\n3. There shall not be implied in any contract for the carriage of goods by sea to which the Rules apply any absolute undertaking by the carrier of the goods to provide a seaworthy ship.\n\nStatement as to application of Rules to be included in bills of lading\n4. \tEvery bill of lading, or similar document of title, issued in Bangladesh which contains or is evidence of any contract to which the Rules apply, shall contain an express statement that it is to have effect subject to the provisions of the said Rules as applied by this Act.\n\nModification of Article VI of Rules in relation to goods carried in sailing ships and by prescribed routes\n5. \tArticle VI of the Rules shall, in relation to-  (a) \tthe carriage of goods by sea in sailing ships carrying goods from any port in Bangladesh to any other port whether in or outside Bangladesh, and   (b) \tthe carriage of goods by sea in ships carrying goods from a port in Bangladesh notified in this behalf in the official Gazette by the Government to a port  2[in India, Ceylon or Pakistan] specified in the said notification,  have effect as though the said Article referred to goods any class instead of to particular goods and as though the proviso to the second paragraph of the said Article were omitted.\n\nModification of Rules 4 and 5 of Article III in relation to bulk cargoes\n6. Where under the custom of any trade the weight of any bulk cargo inserted in the bill of lading is a weight ascertained or accepted by a third party other than the carrier or the shipper and the fact that the weight is so ascertained or accepted is stated in the bill of lading, then, notwithstanding anything in the Rules, the bill of lading shall not be deemed to be prima facie evidence against the carrier of the receipt of goods of the weight so inserted in the bill of lading, and the accuracy thereof at the time of shipment shall not be deemed to have been guaranteed by the shipper.\n\nSaving and operation\n7.(1) Nothing in this Act shall affect the operation of sections four hundred and forty six to four hundred and fifty, both inclusive, five hundred and two, and five hundred and three of the Merchant Shipping Act, 1894, as amended by any subsequent enactment, or the operation of any other enactment for the time being in force limiting the liability of the owners of sea-going vessels.   \t(2) \tThe Rules shall not be virtue of this Act apply to any contract for the carriage of goods by sea before such day, not being earlier than the first day of January, 1926, as the Government may, by notification in the official Gazette, appoint, nor to any bill of lading or similar document of title issued, whether before or after such day as aforesaid, in pursuance of any such contract as aforesaid.",
  "content_corrected": "The Carriage of Goods by Sea Act, 1925 \n\n                        \n                        \n                    \n                    \n                        \n                        \n                        \n                        \n                        \n                        \n                        \n                        \n                        \n                        \n                        \n                        \n                        \n                             (\n                                \n                                    \n                                    \n                                        \n                                            \n                                            ACT\n                                        \n                                        NO. XXVI OF 1925\n                                    \n                                \n\n                                )\n\n1♣An Act to amend the law with respect to the carriage of goods by sea.\n\n                                    \n                                    \n                                \n                            \n                        \n                        \n                            \n                            \n                                 \tWHEREAS at the International Conference on Maritime Law held at Brussels in October, 1922, the delegates at the Conference, including the delegates representing His majesty, agree unanimously to recommend their respective Governments to adopt as the basis of a convention a draft convention for the unification of certain rules relating to bills of lading;   \tAND WHEREAS at a meeting held at Brussels in October, 1923, the rules contained in the said draft convention were amended by the Committee appointed by said Conference;   \tAND WHEREAS provision has been made by the Carriage of Goods by Sea Act, 1924, that the said rules as so amended and as set out with modifications in the Schedule shall, subject to the provisions of that Act, have the force of law with a view to establishing the responsibilities, liabilities, rights and immunities attaching to carriers under bills of lading;   \tAND WHEREAS it is expedient that like provision should be made in Bangladesh; It is hereby enacted as follows:-\n\n1♣An Act to amend the law with respect to the carriage of goods by sea.\n\nShort title and extent\n1.(1) This Act may be called the Carriage of Goods by Sea Act, 1925.  \t(2) \tIt extends to the whole of Bangladesh.\n\nApplication of Rules\n2. \tSubject to the provisions of this Act, the rules set out in the Schedule (hereinafter referred to as \" the Rules\") shall have effect in relation to and in connection with the carriage of goods by sea in ships carrying goods from any port in Bangladesh to any other port whether in or outside Bangladesh.\n\nAbsolute warranty of seaworthiness not to be implied in contracts to which Rules apply\n3. There shall not be implied in any contract for the carriage of goods by sea to which the Rules apply any absolute undertaking by the carrier of the goods to provide a seaworthy ship.\n\nStatement as to application of Rules to be included in bills of lading\n4. \tEvery bill of lading, or similar document of title, issued in Bangladesh which contains or is evidence of any contract to which the Rules apply, shall contain an express statement that it is to have effect subject to the provisions of the said Rules as applied by this Act.\n\nModification of Article VI of Rules in relation to goods carried in sailing ships and by prescribed routes\n5. \tArticle VI of the Rules shall, in relation to-  (a) \tthe carriage of goods by sea in sailing ships carrying goods from any port in Bangladesh to any other port whether in or outside Bangladesh, and   (b) \tthe carriage of goods by sea in ships carrying goods from a port in Bangladesh notified in this behalf in the official Gazette by the Government to a port  2[in India, Ceylon or Pakistan] specified in the said notification,  have effect as though the said Article referred to goods any class instead of to particular goods and as though the proviso to the second paragraph of the said Article were omitted.\n\nModification of Rules 4 and 5 of Article III in relation to bulk cargoes\n6. Where under the custom of any trade the weight of any bulk cargo inserted in the bill of lading is a weight ascertained or accepted by a third party other than the carrier or the shipper and the fact that the weight is so ascertained or accepted is stated in the bill of lading, then, notwithstanding anything in the Rules, the bill of lading shall not be deemed to be prima facie evidence against the carrier of the receipt of goods of the weight so inserted in the bill of lading, and the accuracy thereof at the time of shipment shall not be deemed to have been guaranteed by the shipper.\n\nSaving and operation\n7.(1) Nothing in this Act shall affect the operation of sections four hundred and forty six to four hundred and fifty, both inclusive, five hundred and two, and five hundred and three of the Merchant Shipping Act, 1894, as amended by any subsequent enactment, or the operation of any other enactment for the time being in force limiting the liability of the owners of sea-going vessels.   \t(2) \tThe Rules shall not be virtue of this Act apply to any contract for the carriage of goods by sea before such day, not being earlier than the first day of January, 1926, as the Government may, by notification in the official Gazette, appoint, nor to any bill of lading or similar document of title issued, whether before or after such day as aforesaid, in pursuance of any such contract as aforesaid.",
  "url": "http://bdlaws.minlaw.gov.bd/act-details-137.html",
  "volume_number": "chronological_index",
  "legal_status": "unknown",
  "temporal_status": "historical_text",
  "temporal_disclaimer": "No inference of current legal force or applicability",
  "lexical_references": {
    "count": 0,
    "method": "pattern-based detection",
    "disclaimer": "Detected via pattern matching. No legal force or applicability implied.",
    "relationship_inference": "explicitly_prohibited",
    "references": []
  },
  "schedules": {
    "representation": "raw_html",
    "extraction_method": "verbatim_dom_capture",
    "processed": false,
    "html_content": null
  },
  "transformation_log": [],
  "protected_sections": [
    "proviso"
  ],
  "numeric_regions": [],
  "data_quality": {
    "completeness": "complete",
    "completeness_disclaimer": "Website representation incomplete; legal completeness unknown",
    "flags": [],
    "ml_risk_factors": [],
    "known_limitations": [
      "Section boundary detection is presentation-dependent",
      "Gazette PDF comparison is out of scope",
      "Amendment chain inference is prohibited",
      "Preamble and enactment clause may not be present in all HTML extractions",
      "Statutory footnotes may be incomplete or missing from source HTML"
    ],
    "ml_usage_warning": "HTML artifacts, encoding noise, and structural gaps are present; suitable only for exploratory retrieval and analysis. Not validated for training or evaluation."
  },
  "extraction_risk": {
    "possible_truncation": false,
    "reason": "none"
  },
  "numeric_representation": [
    "en_digits"
  ],
  "language_distribution": {
    "bn_ratio": 0,
    "en_ratio": 1
  },
  "editorial_content_present": true,
  "source_authority": "bdlaws_html_only",
  "authority_rank": [
    "bdlaws_html"
  ],
  "marker_frequency": {
    "ধারা": {
      "count": 0,
      "method": "raw string frequency, including cross-references"
    },
    "অধ্যায়": {
      "count": 0,
      "method": "raw string frequency"
    },
    "তফসিল": {
      "count": 0,
      "method": "raw string frequency, including schedule references"
    }
  },
  "html_capture_definition": "Browser-rendered DOM text nodes",
  "dom_extraction_method": "textContent",
  "capture_environment": {
    "browser": "Chrome",
    "browser_engine": "Blink",
    "extraction_api": "element.textContent",
    "innerText_forbidden": true
  },
  "content_raw_disclaimer": "Represents browser-parsed DOM text via textContent, not raw HTML or server response bytes",
  "content_raw_sha256": "d440f59d4ef82f2a5c710214505d409393c2239021e96efbdbfd3b2071a9faa8",
  "reference_semantics": "string_match_only",
  "reference_warning": "Keywords detected in proximity to citation strings. No legal relationship, effect, direction, or applicability is implied.",
  "negation_handling": "classification_suppression_only",
  "numeric_integrity": "best_effort_html_only",
  "numeric_warning": "Numeric expressions may be incomplete or malformed due to HTML source limitations",
  "encoding_policy": "preserve_html_artifacts",
  "encoding_scope": "non-semantic, display-only",
  "trust_boundary": {
    "can_trust": [
      "Text appeared on bdlaws HTML pages at extraction time",
      "No semantic rewriting was applied",
      "Transformations are logged"
    ],
    "must_not_trust": [
      "Legal validity",
      "Gazette equivalence",
      "Completeness",
      "Numerical accuracy",
      "Amendment correctness",
      "Post-extraction relevance"
    ]
  },
  "_metadata": {
    "source": "bdlaws.minlaw.gov.bd",
    "source_url": "http://bdlaws.minlaw.gov.bd/act-details-137.html",
    "scraped_at": "2026-04-08T17:05:49.895Z",
    "extracted_at": "2026-04-08T17:05:49.895Z",
    "scraping_method": "manual page-level extraction",
    "tool": "BDLawCorpus",
    "tool_version": "1.3.0",
    "browser_info": "Mozilla/5.0 (Macintosh; Intel Mac OS X 10_15_7) AppleWebKit/537.36 (KHTML, like Gecko) Chrome/146.0.0.0 Safari/537.36",
    "language": "bn",
    "research_purpose": "academic legal corpus construction",
    "robots_txt_status": "not_present",
    "disclaimer": "This tool performs manual extraction of publicly available legal texts for academic research. No automated crawling, modification, or interpretation is performed.",
    "content_hash": "d440f59d4ef82f2a5c710214505d409393c2239021e96efbdbfd3b2071a9faa8",
    "hash_source": "content_raw",
    "schema_version": "3.1"
  }
}